LICENSE
README.md
setup.py
servo_serial/connection.py
servo_serial.egg-info/PKG-INFO
servo_serial.egg-info/SOURCES.txt
servo_serial.egg-info/dependency_links.txt
servo_serial.egg-info/requires.txt
servo_serial.egg-info/top_level.txt