Metadata-Version: 2.1
Name: servo-serial
Version: 0.0.4
Summary: Common class for connect to servo for feetech-servo-sdk version > 0.2.0
Home-page: https://github.com/Adam-Software/Servo-serial
Author: vertigra
Author-email: a@nesterof.com
License: MIT
Platform: UNKNOWN
Classifier: Development Status :: 4 - Beta
Classifier: License :: OSI Approved :: MIT License
Classifier: Operating System :: POSIX :: Other
Classifier: Programming Language :: Python :: 3
License-File: LICENSE
